[{"locale": "Adams County", "county": "Adams County", "official": "Krista Faller", "phones": ["+17015674363"], "faxes": ["+17015672910"], "emails": ["kfaller@nd.gov"], "address": "kfaller@nd.gov"}, {"locale": "Barnes County", "county": "Barnes County", "official": "Beth  M Didier", "phones": ["+17018458500x6666"], "faxes": ["+17018458548"], "emails": ["bdidier@barnescounty.us"], "address": "bdidier@barnescounty.us"}, {"locale": "Benson County", "county": "Benson County", "official": "Bonnie  (Howard) Erickson", "phones": ["+17014735340"], "faxes": ["+17014735571"], "emails": ["bserickson@nd.gov"], "address": "bserickson@nd.gov"}, {"locale": "Billings County", "county": "Billings County", "official": "Marcia  Lamb", "phones": ["+17016234377"], "faxes": ["+17016234761"], "emails": ["mdlamb@nd.gov"], "address": "mdlamb@nd.gov"}, {"locale": "Bottineau County", "county": "Bottineau County", "official": "Lisa  Herbel", "phones": ["+17012282225"], "faxes": ["+17012285181"], "emails": ["lisa.herbel@co.bottineau.nd.us"], "address": "lisa.herbel@co.bottineau.nd.us"}, {"locale": "Bowman County", "county": "Bowman County", "official": "Sandra  (Sandi)  Tivis", "phones": ["+17015233130"], "faxes": ["+17015234899"], "emails": ["stivis@bowmancountynd.gov"], "address": "stivis@bowmancountynd.gov"}, {"locale": "Burke County", "county": "Burke County", "official": "Jeanine  Jensen", "phones": ["+17013772861"], "faxes": ["+17013772866"], "emails": ["jsjensen@nd.gov"], "address": "jsjensen@nd.gov"}, {"locale": "Burleigh County", "county": "Burleigh County", "official": "Allan Vietmeier", "phones": ["+17012226718"], "faxes": ["+17012227528"], "emails": ["burleighauditor@nd.gov"], "address": "burleighauditor@nd.gov"}, {"locale": "Cass County", "county": "Cass County", "official": "Michael  Montplaisir", "phones": ["+17012415600"], "faxes": ["+17012415728"], "emails": ["montplaisirm@casscountynd.gov"], "address": "montplaisirm@casscountynd.gov"}, {"locale": "Cavalier County", "county": "Cavalier County", "official": "Lisa  Gellner", "phones": ["+17012562229"], "faxes": ["+17012562546"], "emails": ["lgellner@nd.gov"], "address": "lgellner@nd.gov"}, {"locale": "Dickey County", "county": "Dickey County", "official": "Wanda Sheppard", "phones": ["+17013493249"], "faxes": ["+17013494639"], "emails": ["wsheppard@nd.gov"], "address": "wsheppard@nd.gov"}, {"locale": "Divide County", "county": "Divide County", "official": "Gayle  Jastrzebski", "phones": ["+17019656351"], "faxes": ["+17019654370"], "emails": ["gjastrze@nd.gov"], "address": "gjastrze@nd.gov"}, {"locale": "Dunn County", "county": "Dunn County", "official": "Tracey  Dolezal", "phones": ["+17015734448"], "faxes": ["+17015734323"], "emails": ["tracey.dolezal@dunncountynd.org"], "address": "tracey.dolezal@dunncountynd.org"}, {"locale": "Eddy County", "county": "Eddy County", "official": "Patty  Williams", "phones": ["+17019472434x2020"], "faxes": ["+17019472279"], "emails": ["pawilliams@nd.gov"], "address": "pawilliams@nd.gov"}, {"locale": "Emmons County", "county": "Emmons County", "official": "Marlys  (Marcy) Ohlhauser", "phones": ["+17012544807"], "faxes": ["+17012544012"], "emails": ["mohlhauser@nd.gov"], "address": "mohlhauser@nd.gov"}, {"locale": "Foster County", "county": "Foster County", "official": "Brad Solberg", "phones": ["+17016522441"], "faxes": ["+17016522173"], "emails": ["bradsolberg@nd.gov"], "address": "bradsolberg@nd.gov"}, {"locale": "Golden Valley County", "county": "Golden Valley County", "official": "Tamra  Sperry", "phones": ["+17018724331"], "faxes": ["+17018724383"], "emails": ["tsperry@nd.gov"], "address": "tsperry@nd.gov"}, {"locale": "Grand Forks County", "county": "Grand Forks County", "official": "Debbie  Nelson", "phones": ["+17017808200"], "faxes": ["+17017808207"], "emails": ["elections@gfcounty.org"], "address": "elections@gfcounty.org"}, {"locale": "Grant County", "county": "Grant County", "official": "Sara Meier", "phones": ["+17016223275"], "faxes": ["+17016223005"], "emails": ["sarmeier@nd.gov"], "address": "sarmeier@nd.gov"}, {"locale": "Griggs County", "county": "Griggs County", "official": "Samantha Larson", "phones": ["+17017973117"], "faxes": ["+17017973587"], "emails": ["samantha.larson@griggscountynd.gov"], "address": "samantha.larson@griggscountynd.gov"}, {"locale": "Hettinger County", "county": "Hettinger County", "official": "Jeri  Schmidt", "phones": ["+17018242515"], "faxes": ["+17018242717"], "emails": ["jerschmidt@nd.gov"], "address": "jerschmidt@nd.gov"}, {"locale": "Kidder County", "county": "Kidder County", "official": "Jean  Schoenhard", "phones": ["+17014754547"], "faxes": ["+17014752202"], "emails": ["jschoenhard@nd.gov"], "address": "jschoenhard@nd.gov"}, {"locale": "LaMoure County", "county": "LaMoure County", "official": "Jan Hamlin", "phones": ["+17018835301"], "faxes": ["+17018834514"], "emails": ["jan.hamlin@co.lamoure.nd.us"], "address": "jan.hamlin@co.lamoure.nd.us"}, {"locale": "Logan County", "county": "Logan County", "official": "Brenda  Fischer", "phones": ["+17017542425"], "faxes": ["+17017542280"], "emails": ["bkfischer@nd.gov"], "address": "bkfischer@nd.gov"}, {"locale": "McHenry County", "county": "McHenry County", "official": "Darlene  Carpenter", "phones": ["+17015375724"], "faxes": ["+17015375969"], "emails": ["dcarpenter@nd.gov"], "address": "dcarpenter@nd.gov"}, {"locale": "McIntosh County", "county": "McIntosh County", "official": "Gina  Ketterling", "phones": ["+17012885141"], "faxes": ["+17012883671"], "emails": ["gketterl@nd.gov"], "address": "gketterl@nd.gov"}, {"locale": "McKenzie County", "county": "McKenzie County", "official": "Erica Johnsrud", "phones": ["+17014443616"], "faxes": ["+17014444113"], "emails": ["ejohnsrud@co.mckenzie.nd.us"], "address": "ejohnsrud@co.mckenzie.nd.us"}, {"locale": "McLean County", "county": "McLean County", "official": "Beth Knutson", "phones": ["+17014628541x825"], "faxes": ["+17014623542"], "emails": ["baknutson@nd.gov"], "address": "baknutson@nd.gov"}, {"locale": "Mercer County", "county": "Mercer County", "official": "Shana  L. Brost", "phones": ["+17017453292"], "faxes": ["+17017453793"], "emails": ["sbrost@nd.gov"], "address": "sbrost@nd.gov"}, {"locale": "Morton County", "county": "Morton County", "official": "Dawn  Rhone", "phones": ["+17016673300"], "faxes": ["+17016673380"], "emails": ["dawn.rhone@mortonnd.org"], "address": "dawn.rhone@mortonnd.org"}, {"locale": "Mountrail County", "county": "Mountrail County", "official": "Stephanie  A Pappa", "phones": ["+17016282145"], "faxes": ["+17016282276"], "emails": ["stephp@co.mountrail.nd.us"], "address": "stephp@co.mountrail.nd.us"}, {"locale": "Nelson County", "county": "Nelson County", "official": "Jenny Wigen", "phones": ["+17012472463"], "faxes": ["+17012472754"], "emails": ["jwigen@nd.gov"], "address": "jwigen@nd.gov"}, {"locale": "Oliver County", "county": "Oliver County", "official": "Judith  Hintz", "phones": ["+17017948721"], "faxes": ["+17017943476"], "emails": ["jhintz@nd.gov"], "address": "jhintz@nd.gov"}, {"locale": "Pembina County", "county": "Pembina County", "official": "Linda  Schlittenhard", "phones": ["+17012654231"], "faxes": ["+17012654876"], "emails": ["lschlitt@nd.gov"], "address": "lschlitt@nd.gov"}, {"locale": "Pierce County", "county": "Pierce County", "official": "Karin  Fursather", "phones": ["+17017765225x2100"], "faxes": ["+17017766942"], "emails": ["kfursath@nd.gov"], "address": "kfursath@nd.gov"}, {"locale": "Ramsey County", "county": "Ramsey County", "official": "Kandy Christopherson", "phones": ["+17016627025"], "faxes": ["+17016627049"], "emails": ["kchristo@nd.gov"], "address": "kchristo@nd.gov"}, {"locale": "Ransom County", "county": "Ransom County", "official": "Nicole Gentzkow", "phones": ["+17016836113"], "faxes": ["+17016835827"], "emails": ["nicole.gentzkow@co.ransom.nd.us"], "address": "nicole.gentzkow@co.ransom.nd.us"}, {"locale": "Renville County", "county": "Renville County", "official": "LeAnn  Pollman", "phones": ["+17017566301"], "faxes": ["+17017567158"], "emails": ["lpollman@nd.gov"], "address": "lpollman@nd.gov"}, {"locale": "Richland County", "county": "Richland County", "official": "Leslie Hage", "phones": ["+17016427700"], "faxes": ["+17016427701"], "emails": ["lhage@co.richland.nd.us"], "address": "lhage@co.richland.nd.us"}, {"locale": "Rolette County", "county": "Rolette County", "official": "Val  McCloud", "phones": ["+17014775665"], "faxes": ["+17014776339"], "emails": ["vmccloud@nd.gov"], "address": "vmccloud@nd.gov"}, {"locale": "Sargent County", "county": "Sargent County", "official": "Pam  Maloney", "phones": ["+17017246241x101"], "faxes": ["+17017246244"], "emails": ["pam.maloney@co.sargent.nd.us"], "address": "pam.maloney@co.sargent.nd.us"}, {"locale": "Sheridan County", "county": "Sheridan County", "official": "Shirley  A Murray", "phones": ["+17013632205"], "faxes": ["+17013632953"], "emails": ["smurray@nd.gov"], "address": "smurray@nd.gov"}, {"locale": "Sioux County", "county": "Sioux County", "official": "Cassie LeCompte", "phones": ["+17018543481"], "faxes": ["+17018543854"], "emails": ["cllecompte@nd.gov"], "address": "cllecompte@nd.gov"}, {"locale": "Slope County", "county": "Slope County", "official": "Lorrie  Buzalsky", "phones": ["+17018796276"], "faxes": ["+17018796278"], "emails": ["lbuzalsky@nd.gov"], "address": "lbuzalsky@nd.gov"}, {"locale": "Stark County", "county": "Stark County", "official": "Kay  Haag", "phones": ["+17014567630"], "faxes": ["+17014567634"], "emails": ["khaag@starkcountynd.gov"], "address": "khaag@starkcountynd.gov"}, {"locale": "Steele County", "county": "Steele County", "official": "Emily  Wigen", "phones": ["+17015242110"], "faxes": ["+17015241715"], "emails": ["ewigen@nd.gov"], "address": "ewigen@nd.gov"}, {"locale": "Stutsman County", "county": "Stutsman County", "official": "Jessica Alonge", "phones": ["+17012529035"], "faxes": ["+17012516310"], "emails": ["jalonge@stutsmancounty.gov"], "address": "jalonge@stutsmancounty.gov"}, {"locale": "Towner County", "county": "Towner County", "official": "Joni  Morlock", "phones": ["+17019684340x1"], "faxes": ["+17019684342"], "emails": ["jmmorlock@nd.gov"], "address": "jmmorlock@nd.gov"}, {"locale": "Traill County", "county": "Traill County", "official": "Glenda Haugen", "phones": ["+17016364458"], "faxes": ["+17016365418"], "emails": ["glenda.haugen@co.traill.nd.us"], "address": "glenda.haugen@co.traill.nd.us"}, {"locale": "Walsh County", "county": "Walsh County", "official": "Kris  Molde", "phones": ["+17013522851"], "faxes": ["+17013523340"], "emails": ["kmolde@nd.gov"], "address": "kmolde@nd.gov"}, {"locale": "Ward County", "county": "Ward County", "official": "Marisa Haman", "phones": ["+17018576420"], "faxes": ["+17018576424"], "emails": ["marisa.haman@wardnd.com"], "address": "marisa.haman@wardnd.com"}, {"locale": "Wells County", "county": "Wells County", "official": "Julie Krosbakken", "phones": ["+17015473521"], "faxes": ["+17015473719"], "emails": ["jkrosbakken@nd.gov"], "address": "jkrosbakken@nd.gov"}, {"locale": "Williams County", "county": "Williams County", "official": "Beth  M Innis", "phones": ["+17015774500"], "faxes": ["+17015774510"], "emails": ["bethi@co.williams.nd.us"], "address": "bethi@co.williams.nd.us"}]